graphql_jwt_oauth2/__init__.py
graphql_jwt_oauth2/constants.py
graphql_jwt_oauth2/decorators.py
graphql_jwt_oauth2/errors.py
graphql_jwt_oauth2/provider.py
graphql_jwt_oauth2/queries.py
graphql_jwt_oauth2/state_manager.py
graphql_jwt_oauth2/utils.py
graphql_jwt_oauth2/django_graphql_jwt_oauth2.egg-info/PKG-INFO
graphql_jwt_oauth2/django_graphql_jwt_oauth2.egg-info/SOURCES.txt
graphql_jwt_oauth2/django_graphql_jwt_oauth2.egg-info/dependency_links.txt
graphql_jwt_oauth2/django_graphql_jwt_oauth2.egg-info/top_level.txt
graphql_jwt_oauth2/providers/__init__.py
graphql_jwt_oauth2/providers/google.py
django_graphql_jwt_oauth2-1.2.3.dist-info/METADATA
django_graphql_jwt_oauth2-1.2.3.dist-info/WHEEL
django_graphql_jwt_oauth2-1.2.3.dist-info/licenses/LICENSE
django_graphql_jwt_oauth2-1.2.3.dist-info/RECORD
