Metadata-Version: 2.1
Name: django-graphql-jwt-oauth2
Version: 1.2.3
Summary: An extension to django-graphene-jwt to allow oauth2 authentication to a Django app.
Project-URL: Homepage, https://github.com/AztlanEngineering/django-graphql-jwt-oauth2
Project-URL: Issues, https://github.com/AztlanEngineering/django-graphql-jwt-oauth2/issues
License-File: LICENSE
Classifier: License :: OSI Approved :: Mozilla Public License 2.0 (MPL 2.0)
Classifier: Operating System :: OS Independent
Classifier: Programming Language :: Python :: 3
Requires-Python: >=3.9
